smisc/__init__.py
smisc/a.py
smisc/aaa.py
smisc-0.1a0.dist-info/LICENSE
smisc-0.1a0.dist-info/METADATA
smisc-0.1a0.dist-info/WHEEL
smisc-0.1a0.dist-info/top_level.txt
smisc-0.1a0.dist-info/RECORD
