Metadata-Version: 2.1
Name: smisc
Version: 0.1a0
Summary: just utils
Home-page: UNKNOWN
Author: sakurain
Author-email: 1457488119@qq.com
License: UNKNOWN
Platform: UNKNOWN
Classifier: Programming Language :: Python :: 3
Classifier: License :: OSI Approved :: Apache Software License
Classifier: Operating System :: OS Independent
Classifier: Development Status :: 1 - Planning
License-File: LICENSE
